<suite name="Playback Web Regression Suite" verbose="1">
    <listeners>
        <listener class-name="com.ooyala.facile.listners.FacileTestListener" />
    </listeners>

    <test name="VTC Web Regression Group">
        <groups>
            <define name="VTC_Regression">
                <include name="Playback" />
                <include name="closedCaption"/>
            </define>
            <run>
                <include name="VTC_Regression" />
            </run>
        </groups>
        <classes>
            <parameter name="testData" value="VTC.xml"/>
            <parameter name="jsFile" value="vtc/vtc.js"/>
            <class name="com.ooyala.playback.VTC.PlaybackDiscoverTests" />
            <class name="com.ooyala.playback.VTC.PlaybackVolumeTests" />
            <class name="com.ooyala.playback.VTC.PlaybackVideoControllerEventTests" />
            <class name="com.ooyala.playback.VTC.PlaybackVerifyEventsTests" />
            <class name="com.ooyala.playback.VTC.PlaybackAutoplayAutoloopTests" />
            <class name="com.ooyala.playback.VTC.PlaybackOverrideEncodingPriorityTests" />
            <class name="com.ooyala.playback.alice.PlaybackClosedCaptionTests" />
        </classes>
    </test>
    <test name = "VTC Multiple Player">
        <groups>
            <define name="VTC_Regression_multiple_player">
                <include name="multiplePlayer"/>
            </define>
            <run>
                <include name = "VTC_Regression_multiple_player"/>
            </run>
        </groups>

        <classes>
            <parameter name="testData" value="VTC.xml"/>
            <parameter name="jsFile" value="vtc/multiplePlayer.js"/>
            <class name="com.ooyala.playback.VTC.PlaybackMultipleV4PlayerTests" />
        </classes>
    </test>

</suite>